sphinx_revealjs_ext_codeblock/__about__.py
sphinx_revealjs_ext_codeblock/__init__.py
sphinx_revealjs_ext_codeblock-0.1.1.dist-info/METADATA
sphinx_revealjs_ext_codeblock-0.1.1.dist-info/WHEEL
sphinx_revealjs_ext_codeblock-0.1.1.dist-info/licenses/LICENSE
sphinx_revealjs_ext_codeblock-0.1.1.dist-info/RECORD
