Metadata-Version: 2.4
Name: sphinx-revealjs-ext-codeblock
Version: 0.1.1
Summary: Extend code-block directive for sphinx-revealjs builder
Project-URL: Documentation, https://github.com/ftnext/sphinx-revealjs-ext-codeblock#readme
Project-URL: Issues, https://github.com/ftnext/sphinx-revealjs-ext-codeblock/issues
Project-URL: Source, https://github.com/ftnext/sphinx-revealjs-ext-codeblock
Author-email: ftnext <takuyafjp+develop@gmail.com>
License-Expression: MIT
License-File: LICENSE
Classifier: Development Status :: 4 - Beta
Classifier: Framework :: Sphinx
Classifier: Framework :: Sphinx :: Extension
Classifier: Intended Audience :: Developers
Classifier: License :: OSI Approved :: MIT License
Classifier: Programming Language :: Python
Classifier: Programming Language :: Python :: 3
Classifier: Programming Language :: Python :: 3 :: Only
Classifier: Programming Language :: Python :: 3.10
Classifier: Programming Language :: Python :: 3.11
Classifier: Programming Language :: Python :: 3.12
Classifier: Programming Language :: Python :: 3.13
Classifier: Programming Language :: Python :: 3.14
Classifier: Topic :: Documentation
Classifier: Topic :: Documentation :: Sphinx
Classifier: Topic :: Software Development :: Documentation
Classifier: Topic :: Text Processing :: Markup :: HTML
Requires-Python: >=3.10
Requires-Dist: sphinx-revealjs
Requires-Dist: sphinxcontrib-extdevhelper-kasane
